nbnode/__init__.py
nbnode/nbnode.py
nbnode/nbnode_trees.py
nbnode/nbnode_util.py
nbnode/apply/__init__.py
nbnode/apply/count_celltree_df.py
nbnode/apply/gate_csv.py
nbnode/apply/gate_pointcloud.py
nbnode/io/__init__.py
nbnode/io/pickle_open_dump.py
nbnode/plot/__init__.py
nbnode/plot/shifted_colormap.py
nbnode/plot/utils.py
nbnode/simulation/FlowSimulationTree.py
nbnode/simulation/TreeMeanDistributionSampler.py
nbnode/simulation/TreeMeanRelative.py
nbnode/simulation/__init__.py
nbnode/simulation/sim_proportional.py
nbnode/simulation/sim_target.py
nbnode/specific_analyses/__init__.py
nbnode/specific_analyses/intraassay/__init__.py
nbnode/specific_analyses/intraassay/gate_init.py
nbnode/specific_analyses/intraassay/sims/__init__.py
nbnode/specific_analyses/intraassay/sims/sim00.py
nbnode/specific_analyses/intraassay/sims/sim01.py
nbnode/specific_analyses/intraassay/sims/sim02.py
nbnode/specific_analyses/intraassay/sims/sim03.py
nbnode/testutil/__init__.py
nbnode/testutil/get_licenses.py
nbnode/testutil/helpers.py
nbnode/utils/__init__.py
nbnode/utils/merge_leaf_nodes.py
nbnode-1.1.0.post2.dist-info/LICENSE.txt
nbnode-1.1.0.post2.dist-info/METADATA
nbnode-1.1.0.post2.dist-info/WHEEL
nbnode-1.1.0.post2.dist-info/top_level.txt
nbnode-1.1.0.post2.dist-info/RECORD
