Metadata-Version: 2.1
Name: nbnode
Version: 1.1.0.post2
Summary: A python package for non-binary trees and simulation of flow cytometry data.
Home-page: https://github.com/ggrlab/nbnode/
Author: gunthergl
Author-email: gunthergl@gmx.net
License: MIT
Project-URL: Documentation, https://ccc_verse.git-pages.uni-regensburg.de/nbnode/
Platform: any
Classifier: Development Status :: 5 - Production/Stable
Classifier: Programming Language :: Python
License-File: LICENSE.txt
Requires-Dist: pandas >=1.2
Requires-Dist: pydotplus
Requires-Dist: datatable
Requires-Dist: anytree
Requires-Dist: matplotlib
Requires-Dist: numpy >=1.21.1
Requires-Dist: dirichlet
Requires-Dist: dtreeviz
Requires-Dist: importlib-metadata ; python_version < "3.8"
Provides-Extra: testing
Requires-Dist: setuptools ; extra == 'testing'
Requires-Dist: pytest ; extra == 'testing'
Requires-Dist: pytest-cov ; extra == 'testing'
Requires-Dist: pytest-testmon ; extra == 'testing'
Requires-Dist: docstr-coverage ; extra == 'testing'
Requires-Dist: nbsphinx ; extra == 'testing'
Requires-Dist: ipykernel ; extra == 'testing'
Requires-Dist: ipython ; extra == 'testing'
Requires-Dist: wand ; extra == 'testing'
